[
  {
    "full_name": "open-sauced/hot",
    "stargazers_count": 41,
    "open_issues_count": 12,
    "forks_count": 19
  },
  {
    "full_name": "NsdHSO/vorkurt",
    "stargazers_count": 1,
    "open_issues_count": 4,
    "forks_count": 3
  },
  {
    "full_name": "dianastanciu-dev/dianastanciu-dev",
    "stargazers_count": 1,
    "open_issues_count": 0,
    "forks_count": 0
  },
  {
    "full_name": "wez/wezterm",
    "stargazers_count": 3194,
    "open_issues_count": 163,
    "forks_count": 174
  },
  {
    "full_name": "wez/wezterm",
    "stargazers_count": 3194,
    "open_issues_count": 163,
    "forks_count": 174
  },
  {
    "full_name": "wez/wezterm",
    "stargazers_count": 3194,
    "open_issues_count": 163,
    "forks_count": 174
  },
  {
    "full_name": "wez/wezterm",
    "stargazers_count": 3194,
    "open_issues_count": 163,
    "forks_count": 174
  },
  {
    "full_name": "wez/wezterm",
    "stargazers_count": 3194,
    "open_issues_count": 163,
    "forks_count": 174
  },
  {
    "full_name": "open-sauced/docs.opensauced.pizza",
    "stargazers_count": 10,
    "open_issues_count": 4,
    "forks_count": 5
  },
  {
    "full_name": "torvalds/linux",
    "stargazers_count": 125679,
    "open_issues_count": 322,
    "forks_count": 41098
  },
  {
    "full_name": "Team-TAU/tau",
    "stargazers_count": 82,
    "open_issues_count": 13,
    "forks_count": 22
  }
]